README.md
setup.py
python_obfuscator/__init__.py
python_obfuscator/obfuscator.py
python_obfuscator/techniques.py
python_obfuscator.egg-info/PKG-INFO
python_obfuscator.egg-info/SOURCES.txt
python_obfuscator.egg-info/dependency_links.txt
python_obfuscator.egg-info/entry_points.txt
python_obfuscator.egg-info/requires.txt
python_obfuscator.egg-info/top_level.txt
python_obfuscator/cli/__init__.py
python_obfuscator/helpers/__init__.py
python_obfuscator/helpers/random_datatype.py
python_obfuscator/helpers/variable_name_generator.py