Metadata-Version: 2.1
Name: python-obfuscator
Version: 0.0.1
Summary: It's a python obfuscator.
Home-page: https://github.com/davidteather/tiktok-api
Author: David Teather
Author-email: contact.davidteather@gmail.com
License: MIT
Download-URL: https://github.com/davidteather/python-obfuscator/tarball/master
Keywords: obfuscator
Platform: UNKNOWN
Classifier: Development Status :: 3 - Alpha
Classifier: Intended Audience :: Developers
Classifier: Topic :: Software Development :: Build Tools
Classifier: License :: OSI Approved :: MIT License
Classifier: Programming Language :: Python :: 3.6
Classifier: Programming Language :: Python :: 3.7
Classifier: Programming Language :: Python :: 3.8
Classifier: Programming Language :: Python :: 3.9
